psynlp/__init__.py
psynlp/core/__init__.py
psynlp/core/fca.py
psynlp/core/fst.py
psynlp/core/oracle.py
psynlp/core/ostia.py
psynlp/helpers/__init__.py
psynlp/helpers/builtins.py
psynlp/helpers/importers.py
psynlp/helpers/misc.py
psynlp/helpers/text.py
psynlp/pipelines/__init__.py
psynlp/pipelines/deterministic.py
psynlp/pipelines/ostia.py
psynlp/pipelines/pac_ostia.py
psynlp-1.0.4.dist-info/DESCRIPTION.rst
psynlp-1.0.4.dist-info/METADATA
psynlp-1.0.4.dist-info/RECORD
psynlp-1.0.4.dist-info/WHEEL
psynlp-1.0.4.dist-info/metadata.json
psynlp-1.0.4.dist-info/top_level.txt
tests/__init__.py
tests/test_pipeline_deterministic.py
tests/test_pipeline_ostia.py
tests/test_pipeline_pac_ostia.py
