Metadata-Version: 2.0
Name: psynlp
Version: 1.0.4
Summary: A python module with Program Synthesis techniques for NLP
Home-page: https://github.com/demfier/psynlp
Author: Gaurav Sahu, Athitya Kumar
Author-email: sahu.gaurav719@gmail.com
License: MIT
Keywords: nlp transducer program-synthesis oracle-learning ostia concept-lattice regex-learning pac-basis concept-learning
Platform: UNKNOWN
Requires-Dist: argparse
Requires-Dist: networkx
Requires-Dist: pandas
